degirum_face/__init__.py
degirum_face/_version.py
degirum_face/configs.py
degirum_face/discovery.py
degirum_face/face_data.py
degirum_face/face_tracking.py
degirum_face/face_tracking_gizmos.py
degirum_face/face_utils.py
degirum_face/logging_config.py
degirum_face/models.yaml
degirum_face/reid_database.py
degirum_face/pyarmor_runtime_009664/__init__.py
degirum_face/pyarmor_runtime_009664/pyarmor_runtime.so
degirum_face-0.6.1.dist-info/METADATA
degirum_face-0.6.1.dist-info/WHEEL
degirum_face-0.6.1.dist-info/top_level.txt
degirum_face-0.6.1.dist-info/RECORD
