Metadata-Version: 2.4
Name: degirum_face
Version: 0.6.1
Summary: DeGirum Face Recognition Package
Home-page: https://hub.degirum.com/
Author: DeGirum Corp
Author-email: support@degirum.com
License: Proprietary (https://docs.degirum.com/pysdk/eula)
Classifier: Programming Language :: Python :: 3
Requires-Python: >=3.9
Requires-Dist: degirum_tools[notifications]>=0.26.1
Requires-Dist: lancedb>=0.26.0
Requires-Dist: winregistry; platform_system == "Windows"
Provides-Extra: cicd
Requires-Dist: twine<7.0.0,>=6.0.0; extra == "cicd"
Requires-Dist: build<2.0.0,>=1.0.0; extra == "cicd"
Requires-Dist: mypy<2.0.0,>=1.0.0; extra == "cicd"
Requires-Dist: flake8<8.0.0,>=7.0.0; extra == "cicd"
Requires-Dist: pyarmor<10.0.0,>=9.0.0; extra == "cicd"
Requires-Dist: types-requests<3.0.0,>=2.0.0; extra == "cicd"
Requires-Dist: coverage<8.0.0,>=7.0.0; extra == "cicd"
Requires-Dist: pytest<10.0.0,>=8.0.0; extra == "cicd"
Dynamic: author
Dynamic: author-email
Dynamic: classifier
Dynamic: description
Dynamic: description-content-type
Dynamic: home-page
Dynamic: license
Dynamic: provides-extra
Dynamic: requires-dist
Dynamic: requires-python
Dynamic: summary
